geoarea/__init__.py
geoarea-0.1.3.dist-info/METADATA
geoarea-0.1.3.dist-info/RECORD
geoarea-0.1.3.dist-info/WHEEL
geoarea-0.1.3.dist-info/top_level.txt
