Metadata-Version: 2.1
Name: geoarea
Version: 0.1.3
Summary: Calculate the area from latitude longitude coordinates list
Home-page: https://github.com/efren-cabrera/geoarea
Author: Efren Cabrera
Author-email: efren@cabrera.dev
License: BSD-2-Clause
Platform: UNKNOWN
Classifier: Intended Audience :: Developers
Classifier: Intended Audience :: Science/Research
Classifier: Topic :: Scientific/Engineering :: GIS
Classifier: License :: OSI Approved :: BSD License
Classifier: Programming Language :: Python :: 3.7
